syspath/__init__.py
syspath/__version__.py
syspath/current_path.py
syspath/git_root.py
syspath/parent_path.py
syspath/py.typed
syspath/syspath.py
syspath-3.0.8.dist-info/licenses/LICENSE
syspath-3.0.8.dist-info/METADATA
syspath-3.0.8.dist-info/WHEEL
syspath-3.0.8.dist-info/top_level.txt
syspath-3.0.8.dist-info/RECORD
