Metadata-Version: 2.4
Name: syspath
Version: 3.0.8
Summary: Easily add common paths to sys.path
Author-email: Albert Wang <git@albertyw.com>
License-Expression: MIT
Project-URL: Homepage, https://github.com/albertyw/syspath
Keywords: python,path,utility
Classifier: Development Status :: 5 - Production/Stable
Classifier: Intended Audience :: Developers
Classifier: Natural Language :: English
Classifier: Topic :: Software Development
Classifier: Programming Language :: Python :: 3
Classifier: Programming Language :: Python :: 3.7
Classifier: Programming Language :: Python :: 3.8
Classifier: Programming Language :: Python :: 3.9
Classifier: Programming Language :: Python :: 3.10
Classifier: Programming Language :: Python :: 3.11
Classifier: Programming Language :: Python :: 3.12
Classifier: Programming Language :: Python :: 3.13
Classifier: Typing :: Typed
Requires-Python: >=3.7
License-File: LICENSE
Provides-Extra: test
Requires-Dist: coverage==7.10.4; extra == "test"
Requires-Dist: ruff==0.12.9; extra == "test"
Requires-Dist: mypy==1.17.1; extra == "test"
Dynamic: license-file
